Workbook

Sheet Finances
A1: Date | B1: Catégorie Recette | C1: Montant Recette | D1: Note | I1: Catégorie | J1: Total
A2: 2026-01-01 | B2: Salaire | C2: 2000 | D2: Salaire Janvier | I2: Nourriture | J2: =SUMIF(B$15:B$34,"Nourriture",C$15:C$34) -> 0
A3: 2026-01-05 | B3: Don | C3: 100 | D3: Donation famille | I3: Transport | J3: =SUMIF(B$15:B$34,"Transport",C$15:C$34) -> 0
A4: 2026-01-10 | B4: Consultation | C4: 300 | D4: Consultation médicale | I4: Loyer | J4: =SUMIF(B$15:B$34,"Loyer",C$15:C$34) -> 0
A5: 2026-01-12 | B5: Autre | C5: 50 | D5: Petit gain | I5: Don | J5: =SUMIF(B$15:B$34,"Don",C$15:C$34) -> 0
A6: 2026-01-15 | B6: Salaire | C6: 2000 | D6: Salaire Février | I6: Offrande | J6: =SUMIF(B$15:B$34,"Offrande",C$15:C$34) -> 0
A7: 2026-01-18 | B7: Don | C7: 200 | D7: Donation église | I7: Habillement | J7: =SUMIF(B$15:B$34,"Habillement",C$15:C$34) -> 0
A8: 2026-01-20 | B8: Consultation | C8: 150 | D8: Consultation santé | I8: Tresse | J8: =SUMIF(B$15:B$34,"Tresse",C$15:C$34) -> 0
A9: 2026-01-22 | B9: Autre | C9: 100 | D9: Vente objet | I9: Beauté | J9: =SUMIF(B$15:B$34,"Beauté",C$15:C$34) -> 0
A10: 2026-01-25 | B10: Salaire | C10: 2000 | D10: Salaire Mars | I10: Prêt | J10: =SUMIF(B$15:B$34,"Prêt",C$15:C$34) -> 0
A11: 2026-01-28 | B11: Don | C11: 50 | D11: Donation amie | I11: Portable | J11: =SUMIF(B$15:B$34,"Portable",C$15:C$34) -> 0
I12: Santé | J12: =SUMIF(B$15:B$34,"Santé",C$15:C$34) -> 0
I13: Autre | J13: =SUMIF(B$15:B$34,"Autre",C$15:C$34) -> 0
A14: Date | B14: Catégorie Dépense | C14: Montant Dépense | D14: Solde | E14: Note
A15: 2026-01-02 | B15: Nourriture | C15: 150 | D15: =SUM(C$2:C$11)-SUM(C$15:C15) -> 0
A16: 2026-01-04 | B16: Transport | C16: 50 | D16: =SUM(C$2:C$11)-SUM(C$15:C16) -> 0
A17: 2026-01-06 | B17: Loyer | C17: 600 | D17: =SUM(C$2:C$11)-SUM(C$15:C17) -> 0
A18: 2026-01-08 | B18: Santé | C18: 100 | D18: =SUM(C$2:C$11)-SUM(C$15:C18) -> 0
A19: 2026-01-10 | B19: Beauté | C19: 80 | D19: =SUM(C$2:C$11)-SUM(C$15:C19) -> 0
A20: 2026-01-12 | B20: Offrande | C20: 50 | D20: =SUM(C$2:C$11)-SUM(C$15:C20) -> 0
A21: 2026-01-15 | B21: Nourriture | C21: 120 | D21: =SUM(C$2:C$11)-SUM(C$15:C21) -> 0
A22: 2026-01-18 | B22: Transport | C22: 60 | D22: =SUM(C$2:C$11)-SUM(C$15:C22) -> 0
A23: 2026-01-20 | B23: Loyer | C23: 600 | D23: =SUM(C$2:C$11)-SUM(C$15:C23) -> 0
A24: 2026-01-22 | B24: Santé | C24: 200 | D24: =SUM(C$2:C$11)-SUM(C$15:C24) -> 0

Sheet Routine
A1: Date | B1: Prière matin | C1: Méditation | D1: Préparation maison | E1: Prière soir | F1: Coucher | G1: Score
A2: 2026-01-01 | B2: Oui | C2: Oui | D2: Oui | E2: Oui | F2: Oui | G2: =SUMPRODUCT((B2:F2="Oui")*20) -> 0
A3: 2026-01-02 | B3: Oui | C3: Non | D3: Oui | E3: Oui | F3: Non | G3: =SUMPRODUCT((B3:F3="Oui")*20) -> 0
A4: 2026-01-03 | B4: Non | C4: Oui | D4: Oui | E4: Non | F4: Oui | G4: =SUMPRODUCT((B4:F4="Oui")*20) -> 0
A5: 2026-01-04 | B5: Oui | C5: Oui | D5: Oui | E5: Oui | F5: Oui | G5: =SUMPRODUCT((B5:F5="Oui")*20) -> 0
A6: 2026-01-05 | B6: Oui | C6: Oui | D6: Non | E6: Oui | F6: Oui | G6: =SUMPRODUCT((B6:F6="Oui")*20) -> 0

Sheet Objectifs
A1: Date | B1: Objectif | C1: Fait | D1: Statut | E1: Score (%)
A2: 2026-01-01 | B2: Méditation 15 min | C2: Oui | D2: =IF(C2="Oui","✅",IF(C2="En cours","⏳","❌")) -> 0 | E2: =IF(C2="Oui",100,IF(C2="En cours",50,0)) -> 0
A3: 2026-01-02 | B3: Lecture Bible 30 min | C3: En cours | D3: =IF(C3="Oui","✅",IF(C3="En cours","⏳","❌")) -> 0 | E3: =IF(C3="Oui",100,IF(C3="En cours",50,0)) -> 0
A4: 2026-01-03 | B4: Balayer maison | C4: Non | D4: =IF(C4="Oui","✅",IF(C4="En cours","⏳","❌")) -> 0 | E4: =IF(C4="Oui",100,IF(C4="En cours",50,0)) -> 0

Sheet Journal spirituel
A1: Date | B1: Entrée spirituelle
A2: 2026-01-01 | B2: Merci Seigneur pour cette journée.
A3: 2026-01-02 | B3: Prière pour sagesse.
A4: 2026-01-03 | B4: Méditation sur gratitude.

Sheet Tableau de bord
A1: Mois | B1: Objectifs (%) | C1: Journal (%) | D1: Routine (%) | E1: Finances (%) | F1: Score global (%)
A2: Jan | B2: =IFERROR(AVERAGEIFS(Objectifs!E:E,Objectifs!A:A,">=2026-02-01",Objectifs!A:A,"<2026-03-01"),0) -> 0 | C2: =IFERROR(COUNTIFS('Journal spirituel'!A:A,">=2026-02-01",'Journal spirituel'!A:A,"<2026-03-01",'Journal spirituel'!B:B,"<>") / COUNTIFS('Journal spirituel'!A:A,">=2026-02-01",'Journal spirituel'!A:A,"<2026-03-01")*100,0) -> 0 | D2: =IFERROR(AVERAGEIFS(Routine!G:G,Routine!A:A,">=2026-02-01",Routine!A:A,"<2026-03-01"),0) -> 0 | E2: =IFERROR(IF(MAX(Finances!D:D)>=0,100,0),0) -> 0 | F2: =AVERAGE(B2:E2) -> 0
A3: Fév | B3: =IFERROR(AVERAGEIFS(Objectifs!E:E,Objectifs!A:A,">=2026-03-01",Objectifs!A:A,"<2026-04-01"),0) -> 0 | C3: =IFERROR(COUNTIFS('Journal spirituel'!A:A,">=2026-03-01",'Journal spirituel'!A:A,"<2026-04-01",'Journal spirituel'!B:B,"<>") / COUNTIFS('Journal spirituel'!A:A,">=2026-03-01",'Journal spirituel'!A:A,"<2026-04-01")*100,0) -> 0 | D3: =IFERROR(AVERAGEIFS(Routine!G:G,Routine!A:A,">=2026-03-01",Routine!A:A,"<2026-04-01"),0) -> 0 | E3: =IFERROR(IF(MAX(Finances!D:D)>=0,100,0),0) -> 0 | F3: =AVERAGE(B3:E3) -> 0
A4: Mar | B4: =IFERROR(AVERAGEIFS(Objectifs!E:E,Objectifs!A:A,">=2026-04-01",Objectifs!A:A,"<2026-05-01"),0) -> 0 | C4: =IFERROR(COUNTIFS('Journal spirituel'!A:A,">=2026-04-01",'Journal spirituel'!A:A,"<2026-05-01",'Journal spirituel'!B:B,"<>") / COUNTIFS('Journal spirituel'!A:A,">=2026-04-01",'Journal spirituel'!A:A,"<2026-05-01")*100,0) -> 0 | D4: =IFERROR(AVERAGEIFS(Routine!G:G,Routine!A:A,">=2026-04-01",Routine!A:A,"<2026-05-01"),0) -> 0 | E4: =IFERROR(IF(MAX(Finances!D:D)>=0,100,0),0) -> 0 | F4: =AVERAGE(B4:E4) -> 0
A5: Avr | B5: =IFERROR(AVERAGEIFS(Objectifs!E:E,Objectifs!A:A,">=2026-05-01",Objectifs!A:A,"<2026-06-01"),0) -> 0 | C5: =IFERROR(COUNTIFS('Journal spirituel'!A:A,">=2026-05-01",'Journal spirituel'!A:A,"<2026-06-01",'Journal spirituel'!B:B,"<>") / COUNTIFS('Journal spirituel'!A:A,">=2026-05-01",'Journal spirituel'!A:A,"<2026-06-01")*100,0) -> 0 | D5: =IFERROR(AVERAGEIFS(Routine!G:G,Routine!A:A,">=2026-05-01",Routine!A:A,"<2026-06-01"),0) -> 0 | E5: =IFERROR(IF(MAX(Finances!D:D)>=0,100,0),0) -> 0 | F5: =AVERAGE(B5:E5) -> 0
A6: Mai | B6: =IFERROR(AVERAGEIFS(Objectifs!E:E,Objectifs!A:A,">=2026-06-01",Objectifs!A:A,"<2026-07-01"),0) -> 0 | C6: =IFERROR(COUNTIFS('Journal spirituel'!A:A,">=2026-06-01",'Journal spirituel'!A:A,"<2026-07-01",'Journal spirituel'!B:B,"<>") / COUNTIFS('Journal spirituel'!A:A,">=2026-06-01",'Journal spirituel'!A:A,"<2026-07-01")*100,0) -> 0 | D6: =IFERROR(AVERAGEIFS(Routine!G:G,Routine!A:A,">=2026-06-01",Routine!A:A,"<2026-07-01"),0) -> 0 | E6: =IFERROR(IF(MAX(Finances!D:D)>=0,100,0),0) -> 0 | F6: =AVERAGE(B6:E6) -> 0
A7: Juin | B7: =IFERROR(AVERAGEIFS(Objectifs!E:E,Objectifs!A:A,">=2026-07-01",Objectifs!A:A,"<2026-08-01"),0) -> 0 | C7: =IFERROR(COUNTIFS('Journal spirituel'!A:A,">=2026-07-01",'Journal spirituel'!A:A,"<2026-08-01",'Journal spirituel'!B:B,"<>") / COUNTIFS('Journal spirituel'!A:A,">=2026-07-01",'Journal spirituel'!A:A,"<2026-08-01")*100,0) -> 0 | D7: =IFERROR(AVERAGEIFS(Routine!G:G,Routine!A:A,">=2026-07-01",Routine!A:A,"<2026-08-01"),0) -> 0 | E7: =IFERROR(IF(MAX(Finances!D:D)>=0,100,0),0) -> 0 | F7: =AVERAGE(B7:E7) -> 0
A8: Juil | B8: =IFERROR(AVERAGEIFS(Objectifs!E:E,Objectifs!A:A,">=2026-08-01",Objectifs!A:A,"<2026-09-01"),0) -> 0 | C8: =IFERROR(COUNTIFS('Journal spirituel'!A:A,">=2026-08-01",'Journal spirituel'!A:A,"<2026-09-01",'Journal spirituel'!B:B,"<>") / COUNTIFS('Journal spirituel'!A:A,">=2026-08-01",'Journal spirituel'!A:A,"<2026-09-01")*100,0) -> 0 | D8: =IFERROR(AVERAGEIFS(Routine!G:G,Routine!A:A,">=2026-08-01",Routine!A:A,"<2026-09-01"),0) -> 0 | E8: =IFERROR(IF(MAX(Finances!D:D)>=0,100,0),0) -> 0 | F8: =AVERAGE(B8:E8) -> 0
A9: Août | B9: =IFERROR(AVERAGEIFS(Objectifs!E:E,Objectifs!A:A,">=2026-09-01",Objectifs!A:A,"<2026-10-01"),0) -> 0 | C9: =IFERROR(COUNTIFS('Journal spirituel'!A:A,">=2026-09-01",'Journal spirituel'!A:A,"<2026-10-01",'Journal spirituel'!B:B,"<>") / COUNTIFS('Journal spirituel'!A:A,">=2026-09-01",'Journal spirituel'!A:A,"<2026-10-01")*100,0) -> 0 | D9: =IFERROR(AVERAGEIFS(Routine!G:G,Routine!A:A,">=2026-09-01",Routine!A:A,"<2026-10-01"),0) -> 0 | E9: =IFERROR(IF(MAX(Finances!D:D)>=0,100,0),0) -> 0 | F9: =AVERAGE(B9:E9) -> 0
A10: Sep | B10: =IFERROR(AVERAGEIFS(Objectifs!E:E,Objectifs!A:A,">=2026-10-01",Objectifs!A:A,"<2026-11-01"),0) -> 0 | C10: =IFERROR(COUNTIFS('Journal spirituel'!A:A,">=2026-10-01",'Journal spirituel'!A:A,"<2026-11-01",'Journal spirituel'!B:B,"<>") / COUNTIFS('Journal spirituel'!A:A,">=2026-10-01",'Journal spirituel'!A:A,"<2026-11-01")*100,0) -> 0 | D10: =IFERROR(AVERAGEIFS(Routine!G:G,Routine!A:A,">=2026-10-01",Routine!A:A,"<2026-11-01"),0) -> 0 | E10: =IFERROR(IF(MAX(Finances!D:D)>=0,100,0),0) -> 0 | F10: =AVERAGE(B10:E10) -> 0
A11: Oct | B11: =IFERROR(AVERAGEIFS(Objectifs!E:E,Objectifs!A:A,">=2026-11-01",Objectifs!A:A,"<2026-12-01"),0) -> 0 | C11: =IFERROR(COUNTIFS('Journal spirituel'!A:A,">=2026-11-01",'Journal spirituel'!A:A,"<2026-12-01",'Journal spirituel'!B:B,"<>") / COUNTIFS('Journal spirituel'!A:A,">=2026-11-01",'Journal spirituel'!A:A,"<2026-12-01")*100,0) -> 0 | D11: =IFERROR(AVERAGEIFS(Routine!G:G,Routine!A:A,">=2026-11-01",Routine!A:A,"<2026-12-01"),0) -> 0 | E11: =IFERROR(IF(MAX(Finances!D:D)>=0,100,0),0) -> 0 | F11: =AVERAGE(B11:E11) -> 0
A12: Nov | B12: =IFERROR(AVERAGEIFS(Objectifs!E:E,Objectifs!A:A,">=2026-12-01",Objectifs!A:A,"<2026-13-01"),0) -> 0 | C12: =IFERROR(COUNTIFS('Journal spirituel'!A:A,">=2026-12-01",'Journal spirituel'!A:A,"<2026-13-01",'Journal spirituel'!B:B,"<>") / COUNTIFS('Journal spirituel'!A:A,">=2026-12-01",'Journal spirituel'!A:A,"<2026-13-01")*100,0) -> 0 | D12: =IFERROR(AVERAGEIFS(Routine!G:G,Routine!A:A,">=2026-12-01",Routine!A:A,"<2026-13-01"),0) -> 0 | E12: =IFERROR(IF(MAX(Finances!D:D)>=0,100,0),0) -> 0 | F12: =AVERAGE(B12:E12) -> 0
A13: Déc | B13: =IFERROR(AVERAGEIFS(Objectifs!E:E,Objectifs!A:A,">=2026-13-01",Objectifs!A:A,"<2026-14-01"),0) -> 0 | C13: =IFERROR(COUNTIFS('Journal spirituel'!A:A,">=2026-13-01",'Journal spirituel'!A:A,"<2026-14-01",'Journal spirituel'!B:B,"<>") / COUNTIFS('Journal spirituel'!A:A,">=2026-13-01",'Journal spirituel'!A:A,"<2026-14-01")*100,0) -> 0 | D13: =IFERROR(AVERAGEIFS(Routine!G:G,Routine!A:A,">=2026-13-01",Routine!A:A,"<2026-14-01"),0) -> 0 | E13: =IFERROR(IF(MAX(Finances!D:D)>=0,100,0),0) -> 0 | F13: =AVERAGE(B13:E13) -> 0
